pyresume/__init__.py
pyresume/pyresume.py
pyresume/utils.py
pyresume/cli/__init__.py
pyresume/cli/validation.py
pyresume/templates/standard.tex
pyresume-0.1.3.dist-info/METADATA
pyresume-0.1.3.dist-info/RECORD
pyresume-0.1.3.dist-info/WHEEL
pyresume-0.1.3.dist-info/entry_points.txt
pyresume-0.1.3.dist-info/top_level.txt
