Metadata-Version: 1.1
Name: pyresume
Version: 0.1.3
Summary: Populate a predefined LaTeX template with contents defined in YAML to build your resume.
Home-page: https://github.com/waynr/pyresume
Author: Wayne Warren
Author-email: wayne.warren.s@gmail.com
License: GNU General Public License v3
Keywords: pyresume
Platform: UNKNOWN
Classifier: Development Status :: 2 - Pre-Alpha
Classifier: Intended Audience :: Developers
Classifier: License :: OSI Approved :: GNU General Public License v3 (GPLv3)
Classifier: Natural Language :: English
Classifier: Programming Language :: Python :: 3
Classifier: Programming Language :: Python :: 3.5
